aerobridge_py/__init__.py
aerobridge_py/aerobridgetools.py
aerobridge-0.0.1.dist-info/LICENSE
aerobridge-0.0.1.dist-info/METADATA
aerobridge-0.0.1.dist-info/WHEEL
aerobridge-0.0.1.dist-info/top_level.txt
aerobridge-0.0.1.dist-info/RECORD
