Metadata-Version: 2.1
Name: aerobridge
Version: 0.0.1
Summary: Useful tools to work with Aerobridge APIs in Python
Home-page: https://github.com/openskies-sh/aerobridge_py
Author: Dr. Hrishikesh Ballal
Author-email: hrishikeshballal@yahoo.com
License: Apache-2.0
Download-URL: https://pypi.org/project/aerobridge_py/
Keywords: Management Server,Aerobridge,Drones,Drone
Platform: UNKNOWN
License-File: LICENSE
Requires-Dist: requests (==2.27.1)
